veritasai/__init__.py
veritasai/claim_extractor.py
veritasai/claim_verifier.py
veritasai/evidence_retriever.py
veritasai/veritasai.py
veritasai-0.1.20.dist-info/licenses/LICENSE
veritasai-0.1.20.dist-info/METADATA
veritasai-0.1.20.dist-info/WHEEL
veritasai-0.1.20.dist-info/top_level.txt
veritasai-0.1.20.dist-info/RECORD
