Metadata-Version: 2.4
Name: veritasai
Version: 0.1.20
Summary: Python utilities for veritasai (edit this description)
Home-page: https://github.com/sopolat/veritasai
Download-URL: https://github.com/sopolat/veritasai/archive/refs/tags/v0.1.tar.gz
Author: Suleyman Olcay Polat
Author-email: suleyman.olcay.polat@gmail.com
License: MIT License
Project-URL: Homepage, https://github.com/sopolat/veritasai
Project-URL: Repository, https://github.com/sopolat/veritasai
Project-URL: Issues, https://github.com/sopolat/veritasai/issues
Keywords: veritasai
Classifier: License :: OSI Approved :: MIT License
Classifier: Programming Language :: Python :: 3.12
Requires-Python: >=3.8
License-File: LICENSE
Requires-Dist: spacy
Requires-Dist: sentence-transformers
Requires-Dist: transformers
Requires-Dist: accelerate
Requires-Dist: bitsandbytes
Requires-Dist: peft
Requires-Dist: torch
Requires-Dist: pandas
Dynamic: author-email
Dynamic: download-url
Dynamic: home-page
Dynamic: license-file
